UptimeReporting/Aggreg.py
UptimeReporting/DateRange.py
UptimeReporting/Report.py
UptimeReporting/TagsGrouping.py
UptimeReporting/UptimeService.py
UptimeReporting/__init__.py
UptimeReporting/__main__.py
UptimeReporting/Templates/csv.j2
UptimeReporting/Templates/html-outlook.j2
UptimeReporting/Templates/html-ts.j2
UptimeReporting/Templates/html.j2
UptimeReporting/UptimeServices/Base.py
UptimeReporting/UptimeServices/Pingdom.py
UptimeReporting/UptimeServices/UptimeRobot.py
UptimeReporting/UptimeServices/__init__.py
uptime_reporting-0.2.0.data/data/CHANGELOG.md
uptime_reporting-0.2.0.data/data/LICENSE
uptime_reporting-0.2.0.data/data/docs/PARAMETERS.md
uptime_reporting-0.2.0.data/data/docs/README.md
uptime_reporting-0.2.0.data/data/docs/TAGSGROUPING.md
uptime_reporting-0.2.0.data/data/docs/TEMPLATES.md
uptime_reporting-0.2.0.data/data/docs/UPTIMESERVICES.md
uptime_reporting-0.2.0.dist-info/LICENSE
uptime_reporting-0.2.0.dist-info/METADATA
uptime_reporting-0.2.0.dist-info/WHEEL
uptime_reporting-0.2.0.dist-info/entry_points.txt
uptime_reporting-0.2.0.dist-info/top_level.txt
uptime_reporting-0.2.0.dist-info/RECORD
