Metadata-Version: 2.1
Name: uptime-reporting
Version: 0.2.0
Summary: service uptime reporting tool
Home-page: https://github.com/giacomolozito/uptime-reporting
Author: Giacomo Lozito
Author-email: giacomo.lozito@gmail.com
License: GPLv3
Keywords: service uptime reporting pingdom
Platform: UNKNOWN
Classifier: Development Status :: 4 - Beta
Classifier: Environment :: Console
Classifier: License :: OSI Approved :: GNU General Public License v3 (GPLv3)
Classifier: Programming Language :: Python :: 3.7
Requires-Python: ~=3.7
Requires-Dist: Jinja2 (>=2.11.1)
Requires-Dist: requests (>=2.23.0)
Requires-Dist: tabulate (>=0.8.7)
